plover_lapwing/__init__.py
plover_lapwing/system.py
plover_lapwing/dictionaries/.gitignore
plover_lapwing/dictionaries/.gitrepo
plover_lapwing/dictionaries/abby-left-hand-modifiers.py
plover_lapwing/dictionaries/american_english_words.txt
plover_lapwing/dictionaries/emily-modifiers.py
plover_lapwing/dictionaries/emily-symbols.py
plover_lapwing/dictionaries/jeff-phrasing.py
plover_lapwing/dictionaries/lapwing-base.json
plover_lapwing/dictionaries/lapwing-commands.json
plover_lapwing/dictionaries/lapwing-lh-numbers.modal
plover_lapwing/dictionaries/lapwing-movement.modal
plover_lapwing/dictionaries/lapwing-numbers.json
plover_lapwing/dictionaries/lapwing-prefixed-proper-nouns.json
plover_lapwing/dictionaries/lapwing-proper-nouns.json
plover_lapwing/dictionaries/lapwing-uk-additions.json
plover_lapwing_aio-1.4.5.dist-info/LICENSE
plover_lapwing_aio-1.4.5.dist-info/METADATA
plover_lapwing_aio-1.4.5.dist-info/WHEEL
plover_lapwing_aio-1.4.5.dist-info/entry_points.txt
plover_lapwing_aio-1.4.5.dist-info/top_level.txt
plover_lapwing_aio-1.4.5.dist-info/zip-safe
plover_lapwing_aio-1.4.5.dist-info/RECORD
