Metadata-Version: 2.2
Name: plover-lapwing-aio
Version: 1.4.5
Summary: Plover plugin to install Lapwing dependencies and extras.
Home-page: https://github.com/aerickt/plover-lapwing-aio
Author: Aerick
Project-URL: Source Code, https://github.com/aerickt/plover-lapwing-aio/
Project-URL: Issue Tracker, https://github.com/aerickt/plover-lapwing-aio/issues
Keywords: plover plover_plugin
Classifier: Development Status :: 4 - Beta
Classifier: Environment :: Plugins
Classifier: Intended Audience :: End Users/Desktop
Classifier: License :: OSI Approved :: GNU General Public License v2 or later (GPLv2+)
Classifier: Operating System :: OS Independent
Classifier: Programming Language :: Python :: 3
Classifier: Programming Language :: Python :: 3.6
Classifier: Programming Language :: Python :: 3.7
Classifier: Programming Language :: Python :: 3.8
Classifier: Programming Language :: Python :: 3.9
Requires-Python: >=3.6
License-File: LICENSE
Requires-Dist: plover>=4.0.0.dev11
Requires-Dist: plover-dict-commands
Requires-Dist: plover-last-translation
Requires-Dist: plover-modal-dictionary
Requires-Dist: plover-python-dictionary
Requires-Dist: plover-stitching
